{
  "questions": [
    {
      "question": "מה הלחץ המקסימלי המומלץ לאחסון בלון גז חנקן במפעל?",
      "answers": [
        "200 בר",
        "150 בר",
        "100 בר",
        "50 בר"
      ],
      "correctAnswer": 0,
      "image": ""
    },
    {
      "question": "מדוע חנקן נחשב למסוכן בסביבות סגורות?",
      "answers": [
        "הוא רעיל",
        "הוא דליק",
        "הוא מחליף את החמצן באוויר",
        "הוא מתפוצץ"
      ],
      "correctAnswer": 2,
      "image": ""
    },
    {
      "question": "באיזה צבע מסומן בלון גז חנקן לפי התקן?",
      "answers": [
        "אדום",
        "שחור",
        "כחול",
        "ירוק"
      ],
      "correctAnswer": 1,
      "image": ""
    },
    {
      "question": "מה חובה לבדוק לפני חיבור רגולטור לבלון גז דחוס?",
      "answers": [
        "משקל הבלון",
        "תאריך התפוגה של הגז",
        "תקינות החוטים והאטמים",
        "צבע הבלון"
      ],
      "correctAnswer": 2,
      "image": ""
    },
    {
      "question": "כמה זמן מומלץ לאוורר חדר לאחר דליפת חנקן?",
      "answers": [
        "5 דקות",
        "15 דקות",
        "30 דקות",
        "שעה"
      ],
      "correctAnswer": 2,
      "image": ""
    },
    {
      "question": "מהו הסימן המרכזי לדליפת גז חנקן?",
      "answers": [
        "ריח חריף",
        "עשן לבן",
        "אין סימן מורגש - הגז חסר ריח וצבע",
        "צליל חזק"
      ],
      "correctAnswer": 2,
      "image": ""
    },
    {
      "question": "מה אסור לעשות בסמוך לאזור אחסון בלוני גז דחוס?",
      "answers": [
        "לעשן או להדליק אש",
        "לדבר בקול רם",
        "לעבוד עם כלים ידניים",
        "ללבוש נעלי בטיחות"
      ],
      "correctAnswer": 0,
      "image": ""
    },
    {
      "question": "מהי הטמפרטורה המקסימלית המותרת לאחסון בלוני גז?",
      "answers": [
        "30°C",
        "40°C",
        "50°C",
        "60°C"
      ],
      "correctAnswer": 2,
      "image": ""
    },
    {
      "question": "איזה ציוד מגן חובה בעת עבודה עם גז דחוס?",
      "answers": [
        "משקפי מגן בלבד",
        "כפפות בלבד",
        "משקפי מגן וכפפות",
        "אין צורך בציוד מגן"
      ],
      "correctAnswer": 2,
      "image": ""
    },
    {
      "question": "מה יש לעשות מיד לאחר גילוי דליפת גז בחדר סגור?",
      "answers": [
        "לסגור את שסתום הגז ולפנות את החדר",
        "להדליק מאוורר",
        "להמתין 5 דקות",
        "לחפש את מקור הדליפה"
      ],
      "correctAnswer": 0,
      "image": ""
    }
  ]
}